_maxtree.so
maxtree/__init__.py
maxtree/component_tree.py
maxtree/maxtree.py
maxtree-0.1.2.dist-info/METADATA
maxtree-0.1.2.dist-info/RECORD
maxtree-0.1.2.dist-info/WHEEL
maxtree-0.1.2.dist-info/top_level.txt
