Metadata-Version: 2.1
Name: maxtree
Version: 0.1.2
Summary: Max Tree algorithm
Home-page: https://github.com/gueguenster/maxtree
Author: Lionel Gueguen
Author-email: gueguenster@gmail.com
License: UNKNOWN
Platform: UNKNOWN
